ratelim/__init__.py
ratelim-0.1.5.dist-info/DESCRIPTION.rst
ratelim-0.1.5.dist-info/METADATA
ratelim-0.1.5.dist-info/metadata.json
ratelim-0.1.5.dist-info/RECORD
ratelim-0.1.5.dist-info/top_level.txt
ratelim-0.1.5.dist-info/WHEEL
