Metadata-Version: 2.0
Name: ratelim
Version: 0.1.5
Summary: Makes it easy to respect rate limits.
Home-page: http://github.com/themiurgo/ratelim
Author: Antonio Lima
Author-email: anto87@gmail.com
License: MIT
Platform: UNKNOWN
Requires-Dist: decorator
